sorting_algorithm_visual/__init__.py
sorting_algorithm_visual/canvas_interface.py
sorting_algorithm_visual/sorting_algorithms.py
sorting_algorithm_visual/visualize.py
sorting_algorithm_visual-0.1.dist-info/METADATA
sorting_algorithm_visual-0.1.dist-info/WHEEL
sorting_algorithm_visual-0.1.dist-info/top_level.txt
sorting_algorithm_visual-0.1.dist-info/RECORD
